negosaki/__init__.py
negosaki/colors.py
negosaki/example.py
negosaki/primes.py
negosaki/utils.py
negosaki_lib-0.0.5.1.dist-info/LICENSE
negosaki_lib-0.0.5.1.dist-info/METADATA
negosaki_lib-0.0.5.1.dist-info/WHEEL
negosaki_lib-0.0.5.1.dist-info/top_level.txt
negosaki_lib-0.0.5.1.dist-info/RECORD
