Metadata-Version: 2.1
Name: negosaki-lib
Version: 0.0.5.1
Summary: A simple python package with some useful functions, etc
Home-page: https://github.com/christofferaakre/negosaki-lib
Author: Christoffer Aakre
Author-email: christoffer.corfield@gmail.com
License: UNKNOWN
Project-URL: Bug Tracker, https://github.com/christofferaakre/negosaki-lib/issues
Platform: UNKNOWN
Classifier: Programming Language :: Python :: 3
Classifier: License :: OSI Approved :: MIT License
Classifier: Operating System :: OS Independent
Requires-Python: >=3.6
License-File: LICENSE
